azure/mgmt/quantum/__init__.py
azure/mgmt/quantum/_azure_quantum_mgmt_client.py
azure/mgmt/quantum/_configuration.py
azure/mgmt/quantum/_patch.py
azure/mgmt/quantum/_serialization.py
azure/mgmt/quantum/_vendor.py
azure/mgmt/quantum/_version.py
azure/mgmt/quantum/py.typed
azure/mgmt/quantum/aio/__init__.py
azure/mgmt/quantum/aio/_azure_quantum_mgmt_client.py
azure/mgmt/quantum/aio/_configuration.py
azure/mgmt/quantum/aio/_patch.py
azure/mgmt/quantum/aio/operations/__init__.py
azure/mgmt/quantum/aio/operations/_offerings_operations.py
azure/mgmt/quantum/aio/operations/_operations.py
azure/mgmt/quantum/aio/operations/_patch.py
azure/mgmt/quantum/aio/operations/_workspace_operations.py
azure/mgmt/quantum/aio/operations/_workspaces_operations.py
azure/mgmt/quantum/models/__init__.py
azure/mgmt/quantum/models/_azure_quantum_mgmt_client_enums.py
azure/mgmt/quantum/models/_models_py3.py
azure/mgmt/quantum/models/_patch.py
azure/mgmt/quantum/operations/__init__.py
azure/mgmt/quantum/operations/_offerings_operations.py
azure/mgmt/quantum/operations/_operations.py
azure/mgmt/quantum/operations/_patch.py
azure/mgmt/quantum/operations/_workspace_operations.py
azure/mgmt/quantum/operations/_workspaces_operations.py
azure_mgmt_quantum-1.0.0b5.dist-info/LICENSE
azure_mgmt_quantum-1.0.0b5.dist-info/METADATA
azure_mgmt_quantum-1.0.0b5.dist-info/WHEEL
azure_mgmt_quantum-1.0.0b5.dist-info/top_level.txt
azure_mgmt_quantum-1.0.0b5.dist-info/RECORD
